m3_users/__init__.py
m3_users/api.py
m3_users/app_meta.py
m3_users/constants.py
m3_users/helpers.py
m3_users/metaroles.py
m3_users/models.py
m3_users/permissions.py
m3_users/roles.py
m3_users/ui.py
m3_users/users.py
m3_users/version.py
m3_users/migrations/0001_initial.py
m3_users/migrations/0002_assignedrole_user.py
m3_users/migrations/__init__.py
m3_users/south_migrations/0001_initial.py
m3_users/south_migrations/__init__.py
m3_users/templates/m3-users/edit-role-window.js
m3_users/templates/m3-users/roles-list-window.js
m3_users/templates/m3-users/select-users-window.js
m3_users-2.4.0.dist-info/licenses/LICENSE
tests/__init__.py
tests/manage.py
tests/prepare_env.py
tests/settings.py
tests/shell.sh
tests/test.sh
tests/urls.py
tests/version.py
tests/core/__init__.py
tests/core/tests.py
m3_users-2.4.0.dist-info/METADATA
m3_users-2.4.0.dist-info/WHEEL
m3_users-2.4.0.dist-info/dependency_links.txt
m3_users-2.4.0.dist-info/top_level.txt
m3_users-2.4.0.dist-info/RECORD
